README.txt
setup.cfg
setup.py
Products/__init__.py
Products/__init__.pyc
Products.republisher.egg-info/PKG-INFO
Products.republisher.egg-info/SOURCES.txt
Products.republisher.egg-info/dependency_links.txt
Products.republisher.egg-info/entry_points.txt
Products.republisher.egg-info/namespace_packages.txt
Products.republisher.egg-info/not-zip-safe
Products.republisher.egg-info/paster_plugins.txt
Products.republisher.egg-info/requires.txt
Products.republisher.egg-info/top_level.txt
Products/republisher/__init__.py
Products/republisher/configure.zcml
Products/republisher/controlpanel.py
Products/republisher/events.py
Products/republisher/interfaces.py
Products/republisher/republisher.py
Products/republisher/republisherprefs.py
Products/republisher/tests.py
Products/republisher/uploadr.py
Products/republisher/xmltramp.py
Products/republisher/profiles/default/controlpanel.xml
Products/republisher/profiles/default/metadata.xml
Products/republisher/profiles/default/registry.xml
docs/HISTORY.txt
docs/INSTALL.txt
docs/LICENSE.GPL
docs/LICENSE.txt