Metadata-Version: 1.0
Name: Products.republisher
Version: 0.2
Summary: republishes content from a plone site into social networks
Home-page: http://svn.v2.nl/plone/Products.republisher
Author: UNKNOWN
Author-email: UNKNOWN
License: GPL
Platform: UNKNOWN
Classifier: Framework :: Plone
Classifier: Programming Language :: Python
